{"_type":"export","__export_format":4,"__export_date":"2022-03-09T08:44:22.176Z","__export_source":"insomnia.desktop.app:v2022.1.0","resources":[{"_id":"req_83709087dd8b4452a4a6e90859335399","parentId":"wrk_d8ea9a39c7e14b9895bf9f48c57e0f27","modified":1646781060217,"created":1646566552500,"url":"http://localhost:500/v1/Delivery","name":"GetPoints","description":"","method":"GET","body":{},"parameters":[],"headers":[],"authentication":{"type":"bearer","token":""},"metaSortKey":-1646566552500,"isPrivate":false,"settingStoreCookies":true,"settingSendCookies":true,"settingDisableRenderRequestBody":false,"settingEncodeUrl":true,"settingRebuildPath":true,"settingFollowRedirects":"global","_type":"request"},{"_id":"wrk_d8ea9a39c7e14b9895bf9f48c57e0f27","parentId":null,"modified":1646566482706,"created":1646566482706,"name":"Delivery","description":"","scope":"collection","_type":"workspace"},{"_id":"req_e2bef5ac868042c49afae3568c6c3e87","parentId":"wrk_d8ea9a39c7e14b9895bf9f48c57e0f27","modified":1646681190886,"created":1646566736796,"url":"http://localhost:5000/v1/Delivery/H","name":"GetPointsByNode","description":"","method":"GET","body":{},"parameters":[],"headers":[],"authentication":{},"metaSortKey":-1645263426050.5,"isPrivate":false,"settingStoreCookies":true,"settingSendCookies":true,"settingDisableRenderRequestBody":false,"settingEncodeUrl":true,"settingRebuildPath":true,"settingFollowRedirects":"global","_type":"request"},{"_id":"req_eca82df516fa45ecb6412985d5988192","parentId":"wrk_d8ea9a39c7e14b9895bf9f48c57e0f27","modified":1646567891464,"created":1646567766732,"url":"http://localhost:5000/v1/Delivery/shortdistance/A/D","name":"GetShortDistance","description":"","method":"GET","body":{},"parameters":[],"headers":[],"authentication":{},"metaSortKey":-1645914989275.25,"isPrivate":false,"settingStoreCookies":true,"settingSendCookies":true,"settingDisableRenderRequestBody":false,"settingEncodeUrl":true,"settingRebuildPath":true,"settingFollowRedirects":"global","_type":"request"},{"_id":"req_bae1672bfde142fb8ff431b849615f35","parentId":"wrk_d8ea9a39c7e14b9895bf9f48c57e0f27","modified":1646725424898,"created":1646567954868,"url":"http://localhost:5000/v1/Delivery","name":"UpdatePoint","description":"","method":"PUT","body":{"mimeType":"application/json","text":"{\n\t\"id\": \"08da0063-7fd0-4478-880f-7dc2d4b04588\",\n\t\"origin\": \"A\",\n\t\"destination\": \"C\",\n\t\"time\": 1,\n\t\"cost\": 22\n}"},"parameters":[],"headers":[{"name":"Content-Type","value":"application/json","id":"pair_96acafa2490047639fda2eb2fbd52b5a"}],"authentication":{"type":"bearer","token":"eyJhbGciOiJIUzI1NiIsInR5cCI6IkpXVCJ9.eyJ1bmlxdWVfbmFtZSI6IkFuZHJlIiwicm9sZSI6IkFkbWluIiwibmJmIjoxNjQ2Njk1MjkxLCJleHAiOjE2NDY2OTg4OTEsImlhdCI6MTY0NjY5NTI5MX0.SLrUX7yLyefQiykNf9oXFpm9kuu4ey7vVQhadO-gvf4"},"metaSortKey":-1644611862825.75,"isPrivate":false,"settingStoreCookies":true,"settingSendCookies":true,"settingDisableRenderRequestBody":false,"settingEncodeUrl":true,"settingRebuildPath":true,"settingFollowRedirects":"global","_type":"request"},{"_id":"req_c70a227be2f9430d893ac17582e7cfaf","parentId":"wrk_d8ea9a39c7e14b9895bf9f48c57e0f27","modified":1646681564814,"created":1646568169844,"url":"http://localhost:5000/v1/Delivery","name":"CreatePoint","description":"","method":"POST","body":{"mimeType":"application/json","text":"{\n\t\"origin\": \"G\",\n\t\"destination\": \"B\",\n\t\"time\": 64,\n\t\"cost\": 73\n}"},"parameters":[],"headers":[{"name":"Content-Type","value":"application/json","id":"pair_96acafa2490047639fda2eb2fbd52b5a"}],"authentication":{},"metaSortKey":-1644286081213.375,"isPrivate":false,"settingStoreCookies":true,"settingSendCookies":true,"settingDisableRenderRequestBody":false,"settingEncodeUrl":true,"settingRebuildPath":true,"settingFollowRedirects":"global","_type":"request"},{"_id":"req_541d00317fc24f628f481ebeb8bc05b9","parentId":"wrk_d8ea9a39c7e14b9895bf9f48c57e0f27","modified":1646681078106,"created":1646568353064,"url":"http://localhost:5000/v1/Delivery/c/b","name":"DeletePoint","description":"","method":"DELETE","body":{},"parameters":[],"headers":[],"authentication":{},"metaSortKey":-1644448972019.5625,"isPrivate":false,"settingStoreCookies":true,"settingSendCookies":true,"settingDisableRenderRequestBody":false,"settingEncodeUrl":true,"settingRebuildPath":true,"settingFollowRedirects":"global","_type":"request"},{"_id":"req_e62a7892354f4e2f8fd4cffbc60182b4","parentId":"wrk_d8ea9a39c7e14b9895bf9f48c57e0f27","modified":1646776567415,"created":1646690787048,"url":"http://localhost:5000/v1/User","name":"UserAdd","description":"","method":"POST","body":{"mimeType":"application/json","text":"{\n\t\"name\": \"Andre2\",\n\t\"passCode\": \"12345\",\n\t\"role\": \"Customer\"\n}"},"parameters":[],"headers":[{"name":"Content-Type","value":"application/json","id":"pair_96acafa2490047639fda2eb2fbd52b5a"}],"authentication":{},"metaSortKey":-1644123190407.1875,"isPrivate":false,"settingStoreCookies":true,"settingSendCookies":true,"settingDisableRenderRequestBody":false,"settingEncodeUrl":true,"settingRebuildPath":true,"settingFollowRedirects":"global","_type":"request"},{"_id":"req_30a2739a2e3f473cb8a27fa03e7c6e8a","parentId":"wrk_d8ea9a39c7e14b9895bf9f48c57e0f27","modified":1646690906363,"created":1646690872940,"url":"http://localhost:5000/v1/User/08da0086-dcb7-4e15-87c7-3ac020ea811d","name":"UserDelete","description":"","method":"DELETE","body":{},"parameters":[],"headers":[],"authentication":{},"metaSortKey":-1644204635810.2812,"isPrivate":false,"settingStoreCookies":true,"settingSendCookies":true,"settingDisableRenderRequestBody":false,"settingEncodeUrl":true,"settingRebuildPath":true,"settingFollowRedirects":"global","_type":"request"},{"_id":"req_5718adfb985d4cd3bb35f740a6fd37cd","parentId":"wrk_d8ea9a39c7e14b9895bf9f48c57e0f27","modified":1646691161401,"created":1646691098809,"url":"http://localhost:5000/v1/User","name":"UserGetAll","description":"","method":"GET","body":{},"parameters":[],"headers":[],"authentication":{},"metaSortKey":-1644123190357.1875,"isPrivate":false,"settingStoreCookies":true,"settingSendCookies":true,"settingDisableRenderRequestBody":false,"settingEncodeUrl":true,"settingRebuildPath":true,"settingFollowRedirects":"global","_type":"request"},{"_id":"req_5520948b740d4939b9227174b6bb0b98","parentId":"wrk_d8ea9a39c7e14b9895bf9f48c57e0f27","modified":1646691187386,"created":1646691170523,"url":"http://localhost:5000/v1/User/08da0087-252f-47c7-8dad-8a020d6900c0","name":"UserGetById","description":"","method":"GET","body":{},"parameters":[],"headers":[],"authentication":{},"metaSortKey":-1644041744979.0938,"isPrivate":false,"settingStoreCookies":true,"settingSendCookies":true,"settingDisableRenderRequestBody":false,"settingEncodeUrl":true,"settingRebuildPath":true,"settingFollowRedirects":"global","_type":"request"},{"_id":"req_52f5657da078470c8de46cb6da734a69","parentId":"wrk_d8ea9a39c7e14b9895bf9f48c57e0f27","modified":1646814139746,"created":1646692838527,"url":"http://localhost:5000/v1/Auth","name":"Authenticate","description":"","method":"POST","body":{"mimeType":"application/json","text":"{\n\t\"name\": \"Andre\",\n\t\"passCode\": \"123456\"\n}"},"parameters":[],"headers":[{"name":"Content-Type","value":"application/json","id":"pair_96acafa2490047639fda2eb2fbd52b5a"}],"authentication":{},"metaSortKey":-1644041744929.0938,"isPrivate":false,"settingStoreCookies":true,"settingSendCookies":true,"settingDisableRenderRequestBody":false,"settingEncodeUrl":true,"settingRebuildPath":true,"settingFollowRedirects":"global","_type":"request"},{"_id":"env_0e541b649f16984b5a389529f1d9079846f823c8","parentId":"wrk_d8ea9a39c7e14b9895bf9f48c57e0f27","modified":1646566482711,"created":1646566482711,"name":"Base Environment","data":{},"dataPropertyOrder":null,"color":null,"isPrivate":false,"metaSortKey":1646566482711,"_type":"environment"},{"_id":"jar_0e541b649f16984b5a389529f1d9079846f823c8","parentId":"wrk_d8ea9a39c7e14b9895bf9f48c57e0f27","modified":1646566482714,"created":1646566482714,"name":"Default Jar","cookies":[],"_type":"cookie_jar"},{"_id":"spc_469d9dbf3f1b46af9008af619331510a","parentId":"wrk_d8ea9a39c7e14b9895bf9f48c57e0f27","modified":1646566482707,"created":1646566482707,"fileName":"Delivery","contents":"","contentType":"yaml","_type":"api_spec"}]}